mo_cache/__init__.py
mo_cache/cache_abstract.py
mo_cache/cache_decorator.py
mo_cache/file_cache.py
mo_cache/logger.py
mo_cache/memory_cache.py
mo_cache/redis_cache.py
mo_cache/utils.py
mo_cache/version.py
test/__init__.py
test/cache_test.py
test/file_cache_test.py
test/memory_cache_test.py
test/redis_cache_test.py
mo_cache-0.0.8.dist-info/METADATA
mo_cache-0.0.8.dist-info/WHEEL
mo_cache-0.0.8.dist-info/top_level.txt
mo_cache-0.0.8.dist-info/zip-safe
mo_cache-0.0.8.dist-info/RECORD
