Metadata-Version: 2.1
Name: mo-cache
Version: 0.0.8
Summary: a simple cache lib support memory、file、redis
Home-page: https://github.com/mouday/mo-cache
Author: Peng Shiyu
Author-email: pengshiyuyx@gmail.com
License: MIT
Keywords: cache
Platform: UNKNOWN
Classifier: Programming Language :: Python :: 3
Classifier: Programming Language :: Python :: 3.7
Requires-Dist: six
Requires-Dist: redis
